pmcrypt/__init__.py
pmcrypt/manager.py
pmcrypt-0.1.0.dist-info/WHEEL
pmcrypt-0.1.0.dist-info/METADATA
pmcrypt-0.1.0.dist-info/RECORD
