Metadata-Version: 2.1
Name: pmcrypt
Version: 0.1.0
Summary: A Python package to properly handle passwords
License: MIT
Author: Vitaman02
Requires-Python: >=3.8.1,<4.0.0
Classifier: License :: OSI Approved :: MIT License
Classifier: Programming Language :: Python :: 3
Classifier: Programming Language :: Python :: 3.9
Classifier: Programming Language :: Python :: 3.10
Classifier: Programming Language :: Python :: 3.11
